refget/__init__.py
refget/_version.py
refget/agents.py
refget/clients.py
refget/const.py
refget/digest_functions.py
refget/examples.py
refget/exceptions.py
refget/models.py
refget/refget.py
refget/refget_router.py
refget/refget_store.py
refget/utilities.py
refget/schemas/AnnotatedSequenceList.yaml
refget/schemas/RawSeqCol.yaml
refget/schemas/SeqColArraySet.yaml
refget/schemas/SeqColArraySetInherent.yaml
refget/schemas/TASeqCol.yaml
refget/schemas/seqcol.json
refget/schemas/seqcol.yaml
refget/schemas/sequence.yaml
refget-0.9.0.dist-info/licenses/LICENSE.txt
refget-0.9.0.dist-info/METADATA
refget-0.9.0.dist-info/WHEEL
refget-0.9.0.dist-info/entry_points.txt
refget-0.9.0.dist-info/top_level.txt
refget-0.9.0.dist-info/RECORD
