Metadata-Version: 2.4
Name: refget
Version: 0.9.0
Summary: Python client for refget
Home-page: https://github.com/refgenie/refget
Author: Nathan Sheffield, Michal Stolarczyk
Author-email: nathan@code.databio.org
License: BSD2
Keywords: genome,assembly,bioinformatics,reference,sequence
Classifier: Development Status :: 4 - Beta
Classifier: License :: OSI Approved :: BSD License
Classifier: Programming Language :: Python :: 3.10
Classifier: Programming Language :: Python :: 3.11
Classifier: Programming Language :: Python :: 3.12
Classifier: Programming Language :: Python :: 3.13
License-File: LICENSE.txt
Requires-Dist: jsonschema
Requires-Dist: gtars>=0.3.0
Requires-Dist: pyyaml
Requires-Dist: requests
Requires-Dist: sqlmodel
Requires-Dist: yacman
Dynamic: author
Dynamic: author-email
Dynamic: classifier
Dynamic: description
Dynamic: description-content-type
Dynamic: home-page
Dynamic: keywords
Dynamic: license
Dynamic: license-file
Dynamic: requires-dist
Dynamic: summary
